Metadata-Version: 2.1
Name: odoo14-addon-document-quick-access-folder-auto-classification
Version: 14.0.2.1.3
Summary: Auto classification of Documents after reading a QR
Home-page: https://github.com/OCA/server-ux
Author: Creu Blanca,Odoo Community Association (OCA)
Author-email: support@odoo-community.org
License: AGPL-3
Platform: UNKNOWN
Classifier: Programming Language :: Python
Classifier: Framework :: Odoo
Classifier: Framework :: Odoo :: 14.0
Classifier: License :: OSI Approved :: GNU Affero General Public License v3
Requires-Python: >=3.6
Requires-Dist: odoo14-addon-document-quick-access
Requires-Dist: odoo14-addon-edi-oca
Requires-Dist: odoo <14.1dev,>=14.0a
Requires-Dist: pdf2image
Requires-Dist: pyzbar
